{
  "item.mastersword.faroreflame": "Farores Flamme",
  "item.mastersword.nayruflame": "Nayrus Flamme",
  "item.mastersword.dinflame": "Dins Flamme",
  "item.mastersword.mysteriousscrap": "geheimnesvoller Legierungsschrott",
  "item.mastersword.kakarikoalloy": "Kakariko Zwergenlegierung",
  "item.mastersword.goddesssword": "Schwert der Göttin",
  "item.mastersword.goddessswordlong": "Langschwert der Göttin",
  "item.mastersword.goddessswordwhite": "Weißes Schwert der Göttin",
  "item.mastersword.mastersword": "Master Schwert",
  "item.mastersword.temperedmastersword": "gehärtetes Master Schwert",
  "item.mastersword.goldenmastersword": "goldenes Master Schwert",
  "item.mastersword.fiercedeitysword": "Doppelhelix Schwert",
  "item.mastersword.truemastersword": "wahres Master Schwert",
  "item.mastersword.hylianshield": "Hylia Shild",
  "item.mastersword.temple_of_time_music_disc": "Tempel der Zeit",
  "item.mastersword.temple_of_time_music_disc.desc": "Tempel der Zeit von Munx",
  "item.mastersword.triforce": "Das Triforce",
  "item.mastersword.triforcecourage": "Triforce des Mutes",
  "item.mastersword.triforcewisdom": "Triforce der Weißheit",
  "item.mastersword.triforcepower": "Triforce der Kraft",
  "item.mastersword.blessed_nether_star": "Gesegneter Nether Stern",
  "item.mastersword.ocarina_fairy": "Feen Ocarina",
  "item.mastersword.ocarina_of_time": "Ocarina der Zeit",
  "block.mastersword.hylian_bottle_healing_fairy": "Fee in einer Flasche",
  "item.mastersword.fairy_spawn_egg": "Heilende Fee Spawn Ei  ",
  "item.mastersword.lon_lon_cow_spawn_egg": "Lon Lon Kuh Spawn Ei",
  "item.mastersword.boomerang": "Bumerang",
  "item.mastersword.fire_rod": "Feuer Stab",
  "item.mastersword.ice_rod": "Eis Stab",
  "item.mastersword.fairy_bow": "Feen Bogen",
  "item.mastersword.bombchu": "WIP - UNFINISHED - NOT FOR USE - Bombchu",
  "item.mastersword.hookshot": "Enterhaken",
  "item.mastersword.longshot": "langer Enterhaken",
  "item.mastersword.sheet_music_zeldas_lullaby": "Notenblatt - Zeldas Wiegenlied",
  "item.mastersword.sheet_music_eponas_song": "Notenblatt - Eponas Lied",
  "item.mastersword.sheet_music_song_of_storms": "Notenblatt - Hymmne des Sturmes",
  "item.mastersword.sheet_music_suns_song": "Notenblatt - Hymmne der Sonne",
  "item.mastersword.lon_lon_milk": "Lon Lon Milch",
  "block.mastersword.hylian_bottle": "Hylia Flasche",
  "block.mastersword.hylian_bottle_prefix": "abgefüllte ",
  "block.mastersword.hylian_bottle_navi": "Navi",
  "block.mastersword.hylian_bottle_tatl": "Tatl",
  "block.mastersword.hylian_bottle_tael": "Tael",
  "block.mastersword.hylian_bottle_ciela": "Ciela",
  "block.mastersword.hylian_bottle_leaf": "Leaf",
  "block.mastersword.hylian_bottle_neri": "Neri",
  "block.mastersword.hylian_bottle_white_fairy": "weiße Fee in einer FLasche",
  "block.mastersword.hylian_bottle_gray_fairy": "graue Fee in einer Flasche",
  "block.mastersword.hylian_bottle_black_fairy": "schwarze Fee in einer Flasche",
  "block.mastersword.hylian_bottle_orange_fairy": "orange Fee in einer Flasche",
  "block.mastersword.hylian_bottle_lime_fairy": "Limettenfee in einer Flasche",
  "block.mastersword.hylian_bottle_green_fairy": "grüne Fee in einer Flasche",
  "block.mastersword.hylian_bottle_cyan_fairy": "cyan-Fee in einer Flasche",
  "block.mastersword.hylian_bottle_purple_fairy": "lila Fee in einer Flasche",
  "block.mastersword.hylian_bottle_magenta_fairy": "magenta Fee in einer Flasche",
  "block.mastersword.hylian_bottle_brown_fairy": "braune Fee in einer Flasche",
  "block.mastersword.hylian_bottle_golden_fairy": "Goldene Fee",
  "block.mastersword.kakariko_ore": "geheimnisvoller Schrottblock",
  "block.mastersword.sword_shrine": "Schwert Podest",
  "block.mastersword.sword_shrine_sword": "Sword Podest mit dem Gottes Schwert",
  "block.mastersword.farore_campfire": "Farores führende Flamme",
  "block.mastersword.nayru_campfire": "Nayrus ewige Flamme",
  "block.mastersword.din_campfire": "Dins feurige Flamme",
  "block.mastersword.farore_fire": "Farores Tempelfeuer - nur Kreativ",
  "block.mastersword.nayru_fire": "Nayrus Tempelfeuer - nur Kreativ",
  "block.mastersword.din_fire": "Dins Tempelfeuer - nur Kreativ",
  "block.mastersword.music_block": "Tempel der Zeit Musik Generations Block",
  "block.mastersword.kakariko_bush": "Kakariko Busch",
  "tooltip.mastersword.rightclick.tooltip1": "ducken gedrückt halten",
  "tooltip.mastersword.rightclick.tooltip2": "und rechtsklick:",
  "tooltip.mastersword.customsword.tooltip1": "Nutzen sie den Mut des antiken Heldens",
  "tooltip.mastersword.customsword.tooltip2": "und entfache ein Sturm aus zeitloser Tapferkeit ",
  "tooltip.mastersword.customsword.tooltip3": " mit grimmiger göttlicher Kraft gesegnet",
  "tooltip.mastersword.customsword.tooltip4": "entfache ein himmlichen Stoß",
  "tooltip.mastersword.customsword.tooltip5": "the valor of ancient heroes",
  "tooltip.mastersword.faroreflame.tooltip1": "Die Wärme von Mut",
  "tooltip.mastersword.faroreflame.tooltip2": "strömt von den Flammen",
  "tooltip.mastersword.nayruflame.tooltip1": "Das Glühen von Weißheit",
  "tooltip.mastersword.nayruflame.tooltip2": "strömt von den Flammen",
  "tooltip.mastersword.dinflame.tooltip1": "Die stechende Hitze von Kraft",
  "tooltip.mastersword.dinflame.tooltip2": "strömt von den FLammen",
  "tooltip.mastersword.hylianshield.tooltip1": "Ein legendäres Schild,",
  "tooltip.mastersword.hylianshield.tooltip2": "bekannt für seine unübertroffene Haltbarkeit und sein makelloses Desisgn.",
  "tooltip.mastersword.hylianshield.tooltip3": "Es symbolisiert die standhafte Mut eines Helden.",
  "tooltip.mastersword.triforce.tooltip1": "Ein heiliges Relikt. Es verkörpert die Enssenz von Mut Weißheit und Kraft.",
  "tooltip.mastersword.triforce.tooltip2": "Es sieht so aus, als würde es auf dein gehärtetes Master Schwert reagieren.",
  "tooltip.mastersword.triforce.tooltip3": "?",
  "tooltip.mastersword.hylian_bottle_healing_fairy.tooltip1": "lass es deine Wunden halten oder behalte es.",
  "tooltip.mastersword.hylian_bottle_healing_fairy.tooltip2": "gebe nicht auf wenn du denkst, es sei alles verloren.",
  "tooltip.mastersword.hylian_bottle.tooltip1": "ducken gedrückt halten um zu plazieren",
  "tooltip.mastersword.hylian_bottle_navi.tooltip1": "Gibt Tips und kämpt zurück, wenn ihr Träger angegriffen wird.",
  "tooltip.mastersword.hylian_bottle_tatl.tooltip1": "späht voraus und informiert dich, wenn Monster in der Nähe sind.",
  "tooltip.mastersword.hylian_bottle_tael.tooltip1": "entfernt temporär schädliche Effekte von ihrem Träger",
  "tooltip.mastersword.hylian_bottle_ciela.tooltip1": "verbessert die Kaft von der Master-Schwert Strahl Attacke ",
  "tooltip.mastersword.hylian_bottle_leaf.tooltip1": "5% Möglichkeit die Hiebkraft vom Träger zu verdoppeln.",
  "tooltip.mastersword.hylian_bottle_neri.tooltip1": "5% Möglichkeit stärker zu werden, bevor man in ein Kampf reinzieht. ",
  "tooltip.mastersword.hylian_bottle_golden_fairy.tooltip1": "kombinierte Fähigkeiten von Feen",
  "tooltip.mastersword.hylian_bottle_golden_fairy.tooltip2": "Eine legendäre Fee, die von den goldenen Göttern geschickt wurde um einem echten Held zuhelfen.",
  "tooltip.mastersword.ocarina_fairy.tooltip1": "Feenmagie verweilt in ihren sanften Tönen.",
  "tooltip.mastersword.ocarina_of_time.tooltip1": "spiele die Melodien von Raum und Zeit",
  "tooltip.mastersword.ocarina.tooltip2": "ausgewählte Hymmne:",
  "tooltip.mastersword.ocarina.song1": "Hymmne der Zeit",
  "tooltip.mastersword.ocarina.song2": "Eponas Lied",
  "tooltip.mastersword.ocarina.song3": "Zeldas Wiegenlied",
  "tooltip.mastersword.ocarina.song4": "Hymmne des Sturmes",
  "tooltip.mastersword.ocarina.song5": "Hymmne der Sonne",
  "message.mastersword.selected_song": "ausgewählte Hymmne: %s",
  "message.mastersword.no_songs_unlocked": "Du hast noch keine Hymmnen erlernt.",
  "tooltip.mastersword.boomerang.tooltip1": "fügt Schaden hinzu und sammelt Items aus einer weiten Entfernung auf",
  "tooltip.mastersword.rod.tooltip1": "Rechtsklick gedrückt halten",
  "tooltip.mastersword.fire_rod.tooltip1": "behersche Dins Feurer und setze ein glühende Feuerball frei.",
  "tooltip.mastersword.ice_rod.tooltip1": "behersche das eisige Gebiet und setze den Zorn der Zoras frei.",
  "tooltip.mastersword.fairy_bow.tooltip1": "ein mächtiger Bogen, eins benutzt von einem Helden verloren in Zeit.",
  "tooltip.mastersword.hookshot.tooltip1": "Ein Werkzeug, eins benutzt von einem antikem Helden,",
  "tooltip.mastersword.hookshot.tooltip2": "um große Distanzen zu überqueren.",
  "tooltip.mastersword.sheetmusicbase.tooltip1": "Benutzen:",
  "tooltip.mastersword.sheetmusicbase.tooltip2": "Lerne diese Hymmne für die Ocarina",
  "tooltip.mastersword.sheetmusiczeldaslullaby.tooltip1": "Eine himmliche Melodie, die durch die königliche Familie vererbt wurde.",
  "tooltip.mastersword.sheetmusiceponassong.tooltip1": "Eine entspannte Melodie, die dein loyales Pferd herbeiruft.",
  "tooltip.mastersword.sheetmusicsongofstorms.tooltip1": "Eine geheimnisvolle Hymmne,die das Wetter beeinflusst.",
  "tooltip.mastersword.sheetmusicsunssong.tooltip1": "Eine antike Hymmne, die den Tag- und Nachtzyklus beeinflusst.",
  "entity.mastersword.navi": "Navi",
  "entity.mastersword.tatl": "Tatl",
  "entity.mastersword.tael": "Tael",
  "entity.mastersword.ciela": "Ciela",
  "entity.mastersword.leaf": "Leaf",
  "entity.mastersword.neri": "Neri",
  "entity.mastersword.white_fairy": "weiße Fee",
  "entity.mastersword.gray_fairy": "graue Fee",
  "entity.mastersword.black_fairy": "schwarze Fee",
  "entity.mastersword.orange_fairy": "orange Fee",
  "entity.mastersword.lime_fairy": "Limettenfee",
  "entity.mastersword.green_fairy": "grüne Fee",
  "entity.mastersword.cyan_fairy": "cyan Fee",
  "entity.mastersword.purple_fairy": "lila Fee",
  "entity.mastersword.magenta_fairy": "magenta Fee",
  "entity.mastersword.brown_fairy": "braune Fee",
  "entity.mastersword.healing_fairy": "heilende Fee",
  "entity.mastersword.ocarinahorse": "Epona",
  "entity.mastersword.lon_lon_cow": "Lon Lon Kuh",
  "creativetab.mastersword_tab": "Die Legende vom Master Schwert",
  "key.category.mastersword.keybinds": "Die Legende vom Master Schwert",
  "key.mastersword.sword_beam": "Schwert Strahl Taste"
}
